{"nodes": [{"id": "save_lidar_dt_jl", "label": "save_lidar_dt.jl", "file_type": "code", "source_file": "save_lidar_dt.jl", "source_location": "L1"}, {"id": "revise", "label": "Revise", "file_type": "code", "source_file": "save_lidar_dt.jl", "source_location": "L4"}, {"id": "pkg", "label": "Pkg", "file_type": "code", "source_file": "save_lidar_dt.jl", "source_location": "L5"}, {"id": "dates", "label": "Dates", "file_type": "code", "source_file": "save_lidar_dt.jl", "source_location": "L7"}, {"id": "jld2", "label": "JLD2", "file_type": "code", "source_file": "save_lidar_dt.jl", "source_location": "L8"}, {"id": "pyplot", "label": "PyPlot", "file_type": "code", "source_file": "save_lidar_dt.jl", "source_location": "L18"}, {"id": "pycall", "label": "PyCall", "file_type": "code", "source_file": "save_lidar_dt.jl", "source_location": "L19"}], "edges": [{"source": "save_lidar_dt_jl", "target": "revise", "relation": "imports", "confidence": "EXTRACTED", "source_file": "save_lidar_dt.jl", "source_location": "L4", "weight": 1.0}, {"source": "save_lidar_dt_jl", "target": "pkg", "relation": "imports", "confidence": "EXTRACTED", "source_file": "save_lidar_dt.jl", "source_location": "L5", "weight": 1.0}, {"source": "save_lidar_dt_jl", "target": "dates", "relation": "imports", "confidence": "EXTRACTED", "source_file": "save_lidar_dt.jl", "source_location": "L7", "weight": 1.0}, {"source": "save_lidar_dt_jl", "target": "jld2", "relation": "imports", "confidence": "EXTRACTED", "source_file": "save_lidar_dt.jl", "source_location": "L8", "weight": 1.0}, {"source": "save_lidar_dt_jl", "target": "pyplot", "relation": "imports", "confidence": "EXTRACTED", "source_file": "save_lidar_dt.jl", "source_location": "L18", "weight": 1.0}, {"source": "save_lidar_dt_jl", "target": "pycall", "relation": "imports", "confidence": "EXTRACTED", "source_file": "save_lidar_dt.jl", "source_location": "L19", "weight": 1.0}, {"source": "save_lidar_dt_jl", "target": "pycall", "relation": "imports", "confidence": "EXTRACTED", "source_file": "save_lidar_dt.jl", "source_location": "L20", "weight": 1.0}]}