{"nodes": [{"id": "codeideas_foo_jl", "label": "foo.jl", "file_type": "code", "source_file": "codeIdeas/foo.jl", "source_location": "L1"}, {"id": "statistics", "label": "Statistics", "file_type": "code", "source_file": "codeIdeas/foo.jl", "source_location": "L1"}, {"id": "foo_robust_mean", "label": "robust_mean()", "file_type": "code", "source_file": "codeIdeas/foo.jl", "source_location": "L7"}, {"id": "foo_robust_median", "label": "robust_median()", "file_type": "code", "source_file": "codeIdeas/foo.jl", "source_location": "L8"}, {"id": "foo_nanmedian", "label": "nanmedian()", "file_type": "code", "source_file": "codeIdeas/foo.jl", "source_location": "L11"}, {"id": "foo_running_median", "label": "running_median()", "file_type": "code", "source_file": "codeIdeas/foo.jl", "source_location": "L18"}, {"id": "foo_estimate_heave_ts", "label": "estimate_heave_ts()", "file_type": "code", "source_file": "codeIdeas/foo.jl", "source_location": "L40"}, {"id": "foo_rain_mask_vertical", "label": "rain_mask_vertical()", "file_type": "code", "source_file": "codeIdeas/foo.jl", "source_location": "L122"}, {"id": "foo_subtract_rain_layers", "label": "subtract_rain_layers!()", "file_type": "code", "source_file": "codeIdeas/foo.jl", "source_location": "L257"}, {"id": "foo_iterative_despike_rain", "label": "iterative_despike_rain()", "file_type": "code", "source_file": "codeIdeas/foo.jl", "source_location": "L289"}], "edges": [{"source": "codeideas_foo_jl", "target": "statistics", "relation": "imports", "confidence": "EXTRACTED", "source_file": "codeIdeas/foo.jl", "source_location": "L1", "weight": 1.0}, {"source": "codeideas_foo_jl", "target": "foo_robust_mean", "relation": "defines", "confidence": "EXTRACTED", "source_file": "codeIdeas/foo.jl", "source_location": "L7", "weight": 1.0}, {"source": "codeideas_foo_jl", "target": "foo_robust_median", "relation": "defines", "confidence": "EXTRACTED", "source_file": "codeIdeas/foo.jl", "source_location": "L8", "weight": 1.0}, {"source": "codeideas_foo_jl", "target": "foo_nanmedian", "relation": "defines", "confidence": "EXTRACTED", "source_file": "codeIdeas/foo.jl", "source_location": "L11", "weight": 1.0}, {"source": "codeideas_foo_jl", "target": "foo_running_median", "relation": "defines", "confidence": "EXTRACTED", "source_file": "codeIdeas/foo.jl", "source_location": "L18", "weight": 1.0}, {"source": "codeideas_foo_jl", "target": "foo_estimate_heave_ts", "relation": "defines", "confidence": "EXTRACTED", "source_file": "codeIdeas/foo.jl", "source_location": "L40", "weight": 1.0}, {"source": "codeideas_foo_jl", "target": "foo_rain_mask_vertical", "relation": "defines", "confidence": "EXTRACTED", "source_file": "codeIdeas/foo.jl", "source_location": "L122", "weight": 1.0}, {"source": "codeideas_foo_jl", "target": "foo_subtract_rain_layers", "relation": "defines", "confidence": "EXTRACTED", "source_file": "codeIdeas/foo.jl", "source_location": "L257", "weight": 1.0}, {"source": "codeideas_foo_jl", "target": "foo_iterative_despike_rain", "relation": "defines", "confidence": "EXTRACTED", "source_file": "codeIdeas/foo.jl", "source_location": "L289", "weight": 1.0}, {"source": "foo_robust_mean", "target": "foo_mean", "relation": "calls", "confidence": "EXTRACTED", "source_file": "codeIdeas/foo.jl", "source_location": "L7", "weight": 1.0}, {"source": "foo_robust_mean", "target": "foo_skipmissing", "relation": "calls", "confidence": "EXTRACTED", "source_file": "codeIdeas/foo.jl", "source_location": "L7", "weight": 1.0}, {"source": "foo_robust_median", "target": "foo_median", "relation": "calls", "confidence": "EXTRACTED", "source_file": "codeIdeas/foo.jl", "source_location": "L8", "weight": 1.0}, {"source": "foo_robust_median", "target": "foo_collect", "relation": "calls", "confidence": "EXTRACTED", "source_file": "codeIdeas/foo.jl", "source_location": "L8", "weight": 1.0}, {"source": "foo_robust_median", "target": "foo_skipmissing", "relation": "calls", "confidence": "EXTRACTED", "source_file": "codeIdeas/foo.jl", "source_location": "L8", "weight": 1.0}, {"source": "foo_nanmedian", "target": "foo_collect", "relation": "calls", "confidence": "EXTRACTED", "source_file": "codeIdeas/foo.jl", "source_location": "L12", "weight": 1.0}, {"source": "foo_nanmedian", "target": "foo_skipmissing", "relation": "calls", "confidence": "EXTRACTED", "source_file": "codeIdeas/foo.jl", "source_location": "L12", "weight": 1.0}, {"source": "foo_nanmedian", "target": "foo_isempty", "relation": "calls", "confidence": "EXTRACTED", "source_file": "codeIdeas/foo.jl", "source_location": "L13", "weight": 1.0}, {"source": "foo_nanmedian", "target": "foo_median", "relation": "calls", "confidence": "EXTRACTED", "source_file": "codeIdeas/foo.jl", "source_location": "L14", "weight": 1.0}, {"source": "foo_running_median", "target": "foo_length", "relation": "calls", "confidence": "EXTRACTED", "source_file": "codeIdeas/foo.jl", "source_location": "L19", "weight": 1.0}, {"source": "foo_running_median", "target": "foo_fill", "relation": "calls", "confidence": "EXTRACTED", "source_file": "codeIdeas/foo.jl", "source_location": "L20", "weight": 1.0}, {"source": "foo_running_median", "target": "foo_div", "relation": "calls", "confidence": "EXTRACTED", "source_file": "codeIdeas/foo.jl", "source_location": "L21", "weight": 1.0}, {"source": "foo_running_median", "target": "foo_max", "relation": "calls", "confidence": "EXTRACTED", "source_file": "codeIdeas/foo.jl", "source_location": "L23", "weight": 1.0}, {"source": "foo_running_median", "target": "foo_min", "relation": "calls", "confidence": "EXTRACTED", "source_file": "codeIdeas/foo.jl", "source_location": "L23", "weight": 1.0}, {"source": "foo_running_median", "target": "foo_nanmedian", "relation": "calls", "confidence": "EXTRACTED", "source_file": "codeIdeas/foo.jl", "source_location": "L24", "weight": 1.0}, {"source": "foo_estimate_heave_ts", "target": "foo_size", "relation": "calls", "confidence": "EXTRACTED", "source_file": "codeIdeas/foo.jl", "source_location": "L47", "weight": 1.0}, {"source": "foo_estimate_heave_ts", "target": "foo_size", "relation": "calls", "confidence": "EXTRACTED", "source_file": "codeIdeas/foo.jl", "source_location": "L48", "weight": 1.0}, {"source": "foo_estimate_heave_ts", "target": "foo_mapslices", "relation": "calls", "confidence": "EXTRACTED", "source_file": "codeIdeas/foo.jl", "source_location": "L51", "weight": 1.0}, {"source": "foo_estimate_heave_ts", "target": "foo_var", "relation": "calls", "confidence": "EXTRACTED", "source_file": "codeIdeas/foo.jl", "source_location": "L51", "weight": 1.0}, {"source": "foo_estimate_heave_ts", "target": "foo_collect", "relation": "calls", "confidence": "EXTRACTED", "source_file": "codeIdeas/foo.jl", "source_location": "L51", "weight": 1.0}, {"source": "foo_estimate_heave_ts", "target": "foo_skipmissing", "relation": "calls", "confidence": "EXTRACTED", "source_file": "codeIdeas/foo.jl", "source_location": "L51", "weight": 1.0}, {"source": "foo_estimate_heave_ts", "target": "foo_vec", "relation": "calls", "confidence": "EXTRACTED", "source_file": "codeIdeas/foo.jl", "source_location": "L52", "weight": 1.0}, {"source": "foo_estimate_heave_ts", "target": "foo_quantile", "relation": "calls", "confidence": "EXTRACTED", "source_file": "codeIdeas/foo.jl", "source_location": "L55", "weight": 1.0}, {"source": "foo_estimate_heave_ts", "target": "foo_findall", "relation": "calls", "confidence": "EXTRACTED", "source_file": "codeIdeas/foo.jl", "source_location": "L56", "weight": 1.0}, {"source": "foo_estimate_heave_ts", "target": "foo_isnan", "relation": "calls", "confidence": "EXTRACTED", "source_file": "codeIdeas/foo.jl", "source_location": "L56", "weight": 1.0}, {"source": "foo_estimate_heave_ts", "target": "foo_quantile", "relation": "calls", "confidence": "EXTRACTED", "source_file": "codeIdeas/foo.jl", "source_location": "L61", "weight": 1.0}, {"source": "foo_estimate_heave_ts", "target": "foo_vec", "relation": "calls", "confidence": "EXTRACTED", "source_file": "codeIdeas/foo.jl", "source_location": "L61", "weight": 1.0}, {"source": "foo_estimate_heave_ts", "target": "foo_median", "relation": "calls", "confidence": "EXTRACTED", "source_file": "codeIdeas/foo.jl", "source_location": "L64", "weight": 1.0}, {"source": "foo_estimate_heave_ts", "target": "foo_skipmissing", "relation": "calls", "confidence": "EXTRACTED", "source_file": "codeIdeas/foo.jl", "source_location": "L64", "weight": 1.0}, {"source": "foo_estimate_heave_ts", "target": "foo_vec", "relation": "calls", "confidence": "EXTRACTED", "source_file": "codeIdeas/foo.jl", "source_location": "L64", "weight": 1.0}, {"source": "foo_estimate_heave_ts", "target": "foo_fill", "relation": "calls", "confidence": "EXTRACTED", "source_file": "codeIdeas/foo.jl", "source_location": "L69", "weight": 1.0}, {"source": "foo_estimate_heave_ts", "target": "foo_isempty", "relation": "calls", "confidence": "EXTRACTED", "source_file": "codeIdeas/foo.jl", "source_location": "L73", "weight": 1.0}, {"source": "foo_estimate_heave_ts", "target": "foo_collect", "relation": "calls", "confidence": "EXTRACTED", "source_file": "codeIdeas/foo.jl", "source_location": "L75", "weight": 1.0}, {"source": "foo_estimate_heave_ts", "target": "foo_skipmissing", "relation": "calls", "confidence": "EXTRACTED", "source_file": "codeIdeas/foo.jl", "source_location": "L75", "weight": 1.0}, {"source": "foo_estimate_heave_ts", "target": "foo_isempty", "relation": "calls", "confidence": "EXTRACTED", "source_file": "codeIdeas/foo.jl", "source_location": "L76", "weight": 1.0}, {"source": "foo_estimate_heave_ts", "target": "foo_median", "relation": "calls", "confidence": "EXTRACTED", "source_file": "codeIdeas/foo.jl", "source_location": "L76", "weight": 1.0}, {"source": "foo_estimate_heave_ts", "target": "foo_sum", "relation": "calls", "confidence": "EXTRACTED", "source_file": "codeIdeas/foo.jl", "source_location": "L83", "weight": 1.0}, {"source": "foo_estimate_heave_ts", "target": "foo_collect", "relation": "calls", "confidence": "EXTRACTED", "source_file": "codeIdeas/foo.jl", "source_location": "L86", "weight": 1.0}, {"source": "foo_estimate_heave_ts", "target": "foo_skipmissing", "relation": "calls", "confidence": "EXTRACTED", "source_file": "codeIdeas/foo.jl", "source_location": "L86", "weight": 1.0}, {"source": "foo_estimate_heave_ts", "target": "foo_isempty", "relation": "calls", "confidence": "EXTRACTED", "source_file": "codeIdeas/foo.jl", "source_location": "L87", "weight": 1.0}, {"source": "foo_estimate_heave_ts", "target": "foo_median", "relation": "calls", "confidence": "EXTRACTED", "source_file": "codeIdeas/foo.jl", "source_location": "L87", "weight": 1.0}, {"source": "foo_estimate_heave_ts", "target": "foo_quantile", "relation": "calls", "confidence": "EXTRACTED", "source_file": "codeIdeas/foo.jl", "source_location": "L92", "weight": 1.0}, {"source": "foo_estimate_heave_ts", "target": "foo_sum", "relation": "calls", "confidence": "EXTRACTED", "source_file": "codeIdeas/foo.jl", "source_location": "L98", "weight": 1.0}, {"source": "foo_estimate_heave_ts", "target": "foo_median", "relation": "calls", "confidence": "EXTRACTED", "source_file": "codeIdeas/foo.jl", "source_location": "L102", "weight": 1.0}, {"source": "foo_estimate_heave_ts", "target": "foo_running_median", "relation": "calls", "confidence": "EXTRACTED", "source_file": "codeIdeas/foo.jl", "source_location": "L107", "weight": 1.0}, {"source": "foo_rain_mask_vertical", "target": "foo_size", "relation": "calls", "confidence": "EXTRACTED", "source_file": "codeIdeas/foo.jl", "source_location": "L134", "weight": 1.0}, {"source": "foo_rain_mask_vertical", "target": "foo_size", "relation": "calls", "confidence": "EXTRACTED", "source_file": "codeIdeas/foo.jl", "source_location": "L135", "weight": 1.0}, {"source": "foo_rain_mask_vertical", "target": "foo_size", "relation": "calls", "confidence": "EXTRACTED", "source_file": "codeIdeas/foo.jl", "source_location": "L137", "weight": 1.0}, {"source": "foo_rain_mask_vertical", "target": "foo_copy", "relation": "calls", "confidence": "EXTRACTED", "source_file": "codeIdeas/foo.jl", "source_location": "L141", "weight": 1.0}, {"source": "foo_rain_mask_vertical", "target": "foo_isnan", "relation": "calls", "confidence": "EXTRACTED", "source_file": "codeIdeas/foo.jl", "source_location": "L143", "weight": 1.0}, {"source": "foo_rain_mask_vertical", "target": "foo_div", "relation": "calls", "confidence": "EXTRACTED", "source_file": "codeIdeas/foo.jl", "source_location": "L151", "weight": 1.0}, {"source": "foo_rain_mask_vertical", "target": "foo_max", "relation": "calls", "confidence": "EXTRACTED", "source_file": "codeIdeas/foo.jl", "source_location": "L155", "weight": 1.0}, {"source": "foo_rain_mask_vertical", "target": "foo_min", "relation": "calls", "confidence": "EXTRACTED", "source_file": "codeIdeas/foo.jl", "source_location": "L155", "weight": 1.0}, {"source": "foo_rain_mask_vertical", "target": "foo_collect", "relation": "calls", "confidence": "EXTRACTED", "source_file": "codeIdeas/foo.jl", "source_location": "L158", "weight": 1.0}, {"source": "foo_rain_mask_vertical", "target": "foo_skipmissing", "relation": "calls", "confidence": "EXTRACTED", "source_file": "codeIdeas/foo.jl", "source_location": "L158", "weight": 1.0}, {"source": "foo_rain_mask_vertical", "target": "foo_isempty", "relation": "calls", "confidence": "EXTRACTED", "source_file": "codeIdeas/foo.jl", "source_location": "L159", "weight": 1.0}, {"source": "foo_rain_mask_vertical", "target": "foo_median", "relation": "calls", "confidence": "EXTRACTED", "source_file": "codeIdeas/foo.jl", "source_location": "L162", "weight": 1.0}, {"source": "foo_rain_mask_vertical", "target": "foo_median", "relation": "calls", "confidence": "EXTRACTED", "source_file": "codeIdeas/foo.jl", "source_location": "L164", "weight": 1.0}, {"source": "foo_rain_mask_vertical", "target": "foo_maximum", "relation": "calls", "confidence": "EXTRACTED", "source_file": "codeIdeas/foo.jl", "source_location": "L166", "weight": 1.0}, {"source": "foo_rain_mask_vertical", "target": "foo_std", "relation": "calls", "confidence": "EXTRACTED", "source_file": "codeIdeas/foo.jl", "source_location": "L166", "weight": 1.0}, {"source": "foo_rain_mask_vertical", "target": "foo_zeros", "relation": "calls", "confidence": "EXTRACTED", "source_file": "codeIdeas/foo.jl", "source_location": "L177", "weight": 1.0}, {"source": "foo_rain_mask_vertical", "target": "foo_max", "relation": "calls", "confidence": "EXTRACTED", "source_file": "codeIdeas/foo.jl", "source_location": "L179", "weight": 1.0}, {"source": "foo_rain_mask_vertical", "target": "foo_min", "relation": "calls", "confidence": "EXTRACTED", "source_file": "codeIdeas/foo.jl", "source_location": "L179", "weight": 1.0}, {"source": "foo_rain_mask_vertical", "target": "foo_isnan", "relation": "calls", "confidence": "EXTRACTED", "source_file": "codeIdeas/foo.jl", "source_location": "L183", "weight": 1.0}, {"source": "foo_rain_mask_vertical", "target": "foo_sum", "relation": "calls", "confidence": "EXTRACTED", "source_file": "codeIdeas/foo.jl", "source_location": "L188", "weight": 1.0}, {"source": "foo_rain_mask_vertical", "target": "foo_isnan", "relation": "calls", "confidence": "EXTRACTED", "source_file": "codeIdeas/foo.jl", "source_location": "L194", "weight": 1.0}, {"source": "foo_rain_mask_vertical", "target": "foo_sign", "relation": "calls", "confidence": "EXTRACTED", "source_file": "codeIdeas/foo.jl", "source_location": "L195", "weight": 1.0}, {"source": "foo_rain_mask_vertical", "target": "foo_sum", "relation": "calls", "confidence": "EXTRACTED", "source_file": "codeIdeas/foo.jl", "source_location": "L197", "weight": 1.0}, {"source": "foo_rain_mask_vertical", "target": "foo_sum", "relation": "calls", "confidence": "EXTRACTED", "source_file": "codeIdeas/foo.jl", "source_location": "L197", "weight": 1.0}, {"source": "foo_rain_mask_vertical", "target": "foo_zeros", "relation": "calls", "confidence": "EXTRACTED", "source_file": "codeIdeas/foo.jl", "source_location": "L202", "weight": 1.0}, {"source": "foo_rain_mask_vertical", "target": "foo_max", "relation": "calls", "confidence": "EXTRACTED", "source_file": "codeIdeas/foo.jl", "source_location": "L204", "weight": 1.0}, {"source": "foo_rain_mask_vertical", "target": "foo_max", "relation": "calls", "confidence": "EXTRACTED", "source_file": "codeIdeas/foo.jl", "source_location": "L210", "weight": 1.0}, {"source": "foo_rain_mask_vertical", "target": "foo_max", "relation": "calls", "confidence": "EXTRACTED", "source_file": "codeIdeas/foo.jl", "source_location": "L215", "weight": 1.0}, {"source": "foo_rain_mask_vertical", "target": "foo_max", "relation": "calls", "confidence": "EXTRACTED", "source_file": "codeIdeas/foo.jl", "source_location": "L221", "weight": 1.0}, {"source": "foo_rain_mask_vertical", "target": "foo_falses", "relation": "calls", "confidence": "EXTRACTED", "source_file": "codeIdeas/foo.jl", "source_location": "L229", "weight": 1.0}, {"source": "foo_subtract_rain_layers", "target": "foo_size", "relation": "calls", "confidence": "EXTRACTED", "source_file": "codeIdeas/foo.jl", "source_location": "L258", "weight": 1.0}, {"source": "foo_subtract_rain_layers", "target": "foo_copy", "relation": "calls", "confidence": "EXTRACTED", "source_file": "codeIdeas/foo.jl", "source_location": "L259", "weight": 1.0}, {"source": "foo_subtract_rain_layers", "target": "foo_collect", "relation": "calls", "confidence": "EXTRACTED", "source_file": "codeIdeas/foo.jl", "source_location": "L270", "weight": 1.0}, {"source": "foo_subtract_rain_layers", "target": "foo_skipmissing", "relation": "calls", "confidence": "EXTRACTED", "source_file": "codeIdeas/foo.jl", "source_location": "L270", "weight": 1.0}, {"source": "foo_subtract_rain_layers", "target": "foo_length", "relation": "calls", "confidence": "EXTRACTED", "source_file": "codeIdeas/foo.jl", "source_location": "L271", "weight": 1.0}, {"source": "foo_subtract_rain_layers", "target": "foo_median", "relation": "calls", "confidence": "EXTRACTED", "source_file": "codeIdeas/foo.jl", "source_location": "L272", "weight": 1.0}, {"source": "foo_subtract_rain_layers", "target": "foo_mean", "relation": "calls", "confidence": "EXTRACTED", "source_file": "codeIdeas/foo.jl", "source_location": "L272", "weight": 1.0}, {"source": "foo_subtract_rain_layers", "target": "foo_push", "relation": "calls", "confidence": "EXTRACTED", "source_file": "codeIdeas/foo.jl", "source_location": "L275", "weight": 1.0}, {"source": "foo_iterative_despike_rain", "target": "foo_size", "relation": "calls", "confidence": "EXTRACTED", "source_file": "codeIdeas/foo.jl", "source_location": "L290", "weight": 1.0}, {"source": "foo_iterative_despike_rain", "target": "foo_estimate_heave_ts", "relation": "calls", "confidence": "EXTRACTED", "source_file": "codeIdeas/foo.jl", "source_location": "L292", "weight": 1.0}, {"source": "foo_iterative_despike_rain", "target": "foo_println", "relation": "calls", "confidence": "EXTRACTED", "source_file": "codeIdeas/foo.jl", "source_location": "L294", "weight": 1.0}, {"source": "foo_iterative_despike_rain", "target": "foo_rain_mask_vertical", "relation": "calls", "confidence": "EXTRACTED", "source_file": "codeIdeas/foo.jl", "source_location": "L295", "weight": 1.0}, {"source": "foo_iterative_despike_rain", "target": "foo_copy", "relation": "calls", "confidence": "EXTRACTED", "source_file": "codeIdeas/foo.jl", "source_location": "L297", "weight": 1.0}, {"source": "foo_iterative_despike_rain", "target": "foo_estimate_heave_ts", "relation": "calls", "confidence": "EXTRACTED", "source_file": "codeIdeas/foo.jl", "source_location": "L301", "weight": 1.0}, {"source": "foo_iterative_despike_rain", "target": "foo_all", "relation": "calls", "confidence": "EXTRACTED", "source_file": "codeIdeas/foo.jl", "source_location": "L303", "weight": 1.0}, {"source": "foo_iterative_despike_rain", "target": "foo_maximum", "relation": "calls", "confidence": "EXTRACTED", "source_file": "codeIdeas/foo.jl", "source_location": "L307", "weight": 1.0}, {"source": "foo_iterative_despike_rain", "target": "foo_skipmissing", "relation": "calls", "confidence": "EXTRACTED", "source_file": "codeIdeas/foo.jl", "source_location": "L307", "weight": 1.0}, {"source": "foo_iterative_despike_rain", "target": "foo_println", "relation": "calls", "confidence": "EXTRACTED", "source_file": "codeIdeas/foo.jl", "source_location": "L308", "weight": 1.0}, {"source": "foo_iterative_despike_rain", "target": "foo_isnan", "relation": "calls", "confidence": "EXTRACTED", "source_file": "codeIdeas/foo.jl", "source_location": "L308", "weight": 1.0}, {"source": "foo_iterative_despike_rain", "target": "foo_rain_mask_vertical", "relation": "calls", "confidence": "EXTRACTED", "source_file": "codeIdeas/foo.jl", "source_location": "L313", "weight": 1.0}, {"source": "foo_iterative_despike_rain", "target": "foo_subtract_rain_layers", "relation": "calls", "confidence": "EXTRACTED", "source_file": "codeIdeas/foo.jl", "source_location": "L315", "weight": 1.0}]}